pllpy.so
pllpy-0.2.0.data/scripts/pll
pllpy-0.2.0.dist-info/DESCRIPTION.rst
pllpy-0.2.0.dist-info/METADATA
pllpy-0.2.0.dist-info/RECORD
pllpy-0.2.0.dist-info/WHEEL
pllpy-0.2.0.dist-info/metadata.json
pllpy-0.2.0.dist-info/top_level.txt
