Metadata-Version: 2.0
Name: pllpy
Version: 0.2.0
Summary: Wrapper for Phylogenetic Likelihood Library
Home-page: https://github.com/kgori/pllpy.git
Author: Kevin Gori
Author-email: kgori@ebi.ac.uk
License: UNKNOWN
Platform: UNKNOWN
Requires-Dist: cython
